xcofdk/LICENSE.txt
xcofdk/README.md
xcofdk/__init__.py
xcofdk/_xcofw/_fw/fwssys/assys/fwsubsysshare.py
xcofdk/_xcofw/_fw/fwssys/assys/ifs/__init__.py
xcofdk/_xcofw/_fw/fwssys/assys/ifs/ifdispagent.py
xcofdk/_xcofw/_fw/fwssys/assys/ifs/iffwapiconn.py
xcofdk/_xcofw/_fw/fwssys/assys/ifs/iffwmain.py
xcofdk/_xcofw/_fw/fwssys/assys/ifs/iffwsprocmgr.py
xcofdk/_xcofw/_fw/fwssys/assys/ifs/iffwtask.py
xcofdk/_xcofw/_fw/fwssys/assys/ifs/iftmgrimpl.py
xcofdk/_xcofw/_fw/fwssys/assys/ifs/ifutagent.py
xcofdk/_xcofw/_fw/fwssys/assys/ifs/ifutask.py
xcofdk/_xcofw/_fw/fwssys/assys/ifs/ifutaskconn.py
xcofdk/_xcofw/_fw/fwssys/assys/ifs/ifxprocagent.py
xcofdk/_xcofw/_fw/fwssys/assys/ifs/ifxprocconn.py
xcofdk/_xcofw/_fw/fwssys/assys/ifs/ifxunit.py
xcofdk/_xcofw/_fw/fwssys/assys/ifs/tiflcmgr.py
xcofdk/_xcofw/_fw/fwssys/assys/ifs/tiftmgr.py
xcofdk/_xcofw/_fw/fwssys/fwcore/ssdsupervisor.py
xcofdk/_xcofw/_fw/fwssys/fwcore/base/fsutil.py
xcofdk/_xcofw/_fw/fwssys/fwcore/base/fwargparser.py
xcofdk/_xcofw/_fw/fwssys/fwcore/base/fwcallable.py
xcofdk/_xcofw/_fw/fwssys/fwcore/base/gtimeout.py
xcofdk/_xcofw/_fw/fwssys/fwcore/base/listutil.py
xcofdk/_xcofw/_fw/fwssys/fwcore/base/sigcheck.py
xcofdk/_xcofw/_fw/fwssys/fwcore/base/strutil.py
xcofdk/_xcofw/_fw/fwssys/fwcore/base/timeutil.py
xcofdk/_xcofw/_fw/fwssys/fwcore/base/util.py
xcofdk/_xcofw/_fw/fwssys/fwcore/config/fwcfgdefines.py
xcofdk/_xcofw/_fw/fwssys/fwcore/config/fwconfig.py
xcofdk/_xcofw/_fw/fwssys/fwcore/config/fwsoptionsimpl.py
xcofdk/_xcofw/_fw/fwssys/fwcore/config/fwstartupconfig.py
xcofdk/_xcofw/_fw/fwssys/fwcore/config/fwstartuppolicy.py
xcofdk/_xcofw/_fw/fwssys/fwcore/config/logheadrfmt.py
xcofdk/_xcofw/_fw/fwssys/fwcore/config/ssyscfg/fwssyscbase.py
xcofdk/_xcofw/_fw/fwssys/fwcore/config/ssyscfg/sscipc.py
xcofdk/_xcofw/_fw/fwssys/fwcore/config/ssyscfg/ssclogging.py
xcofdk/_xcofw/_fw/fwssys/fwcore/config/ssyscfg/sscsupervisor.py
xcofdk/_xcofw/_fw/fwssys/fwcore/ipc/ssdipc.py
xcofdk/_xcofw/_fw/fwssys/fwcore/ipc/fws/afwservice.py
xcofdk-3.2.1.dist-info/METADATA
xcofdk-3.2.1.dist-info/WHEEL
xcofdk-3.2.1.dist-info/top_level.txt
xcofdk-3.2.1.dist-info/RECORD
