Metadata-Version: 2.4
Name: xcofdk
Version: 3.2.1
Summary: XCOFDK is a runtime environment to provide multithreading, multiprocessing and life cycle management to programs.
Home-page: https://www.xcofdk.de/
Author: Farzad Safa
Author-email: farzad.safa@xcofdk.de
License: MIT
Platform: posix
Platform: nt
Classifier: Development Status :: 5 - Production/Stable
Classifier: License :: OSI Approved :: MIT License
Classifier: Natural Language :: English
Classifier: Operating System :: POSIX :: Linux
Classifier: Operating System :: Microsoft :: Windows
Classifier: Programming Language :: Python :: 3 :: Only
Classifier: Intended Audience :: Developers
Classifier: Topic :: Software Development
Classifier: Topic :: Software Development :: Libraries :: Application Frameworks
Requires-Python: >=3.8
